[
    {
      "id": 181808,
      "livraisontype": "Livraison",
      "heure": "8h00 - 9h00",
      "client": "Adrien Courtoise",
      "pay": "Paris",
      "address": "55 rue du Faubourg-Saint-Honoré",
      "codepostal": "75008 Paris, France"
    },
    {
      "id": 181809,
      "livraisontype": "Collect",
      "heure": "8h00 - 9h00",
      "client": "Adrien Courtoise",
      "pay": "Paris",
      "address": "55 rue du Faubourg-Saint-Honoré",
      "codepostal": "75008 Paris, France"
    },
    {
      "id": 1818199,
      "livraisontype": "Livraison",
      "heure": "8h00 - 9h00",
      "client": "Adrien Courtoise",
      "pay": "Paris",
      "address": "55 rue du Faubourg-Saint-Honoré",
      "codepostal": "75008 Paris, France"
    },
    {
      "id": 1818,
      "livraisontype": "Livraison",
      "heure": "8h00 - 9h00",
      "client": "Adrien Courtoise",
      "pay": "Paris",
      "address": "55 rue du Faubourg-Saint-Honoré",
      "codepostal": "75008 Paris, France"
    },
    {
      "id": 18,
      "livraisontype": "Collect",
      "heure": "8h00 - 9h00",
      "client": "Adrien Courtoise",
      "pay": "Paris",
      "address": "55 rue du Faubourg-Saint-Honoré",
      "codepostal": "75008 Paris, France"
    },
    {
      "id": 181819999,
      "livraisontype": "Livraison",
      "heure": "8h00 - 9h00",
      "client": "Adrien Courtoise",
      "pay": "Paris",
      "address": "55 rue du Faubourg-Saint-Honoré",
      "codepostal": "75008 Paris, France"
    }
  ]
  
  
  
  
  